{
  "type": "minecraft:entity",
  "pools": [
    {
      "rolls": 1,
      "entries": [
        {
          "type": "minecraft:item",
          "name": "minecraft:emerald",
          "functions": [
            {
              "function": "minecraft:limit_count",
              "limit": 5
            },
            {
              "function": "set_nbt",
              "tag": "{display:{Name:'{\"text\":\"通貨\"}'}}"
            }
          ]
        }
      ]
    },
    {
      "rolls": 1,
      "entries": [
        {
          "type": "minecraft:item",
          "name": "minecraft:gold_block",
          "functions": [
            {
              "function": "minecraft:limit_count",
              "limit": 1
            }
          ]
        }
      ]
    },
    {
      "rolls": 1,
      "entries": [
        {
          "type": "minecraft:item",
          "name": "minecraft:experience_bottle",
          "functions": [
            {
              "function": "minecraft:limit_count",
              "limit": 5
            }
          ]
        }
      ]
    }
  ]
}